edx_lint/__init__.py
edx_lint/__main__.py
edx_lint/configfile.py
edx_lint/metadata.py
edx_lint/tamper_evident.py
edx_lint/write.py
edx_lint/cmd/__init__.py
edx_lint/cmd/amnesty.py
edx_lint/cmd/check.py
edx_lint/cmd/list.py
edx_lint/cmd/main.py
edx_lint/cmd/update.py
edx_lint/cmd/write.py
edx_lint/files/.editorconfig
edx_lint/files/commitlint.config.js
edx_lint/files/common_constraints.txt
edx_lint/files/just_for_testing.txt
edx_lint/files/pylintrc
edx_lint/pylint/__init__.py
edx_lint/pylint/annotations_check.py
edx_lint/pylint/common.py
edx_lint/pylint/getattr_check.py
edx_lint/pylint/i18n_check.py
edx_lint/pylint/layered_test_check.py
edx_lint/pylint/module_trace.py
edx_lint/pylint/plugin.py
edx_lint/pylint/range_check.py
edx_lint/pylint/right_assert_check.py
edx_lint/pylint/super_check.py
edx_lint/pylint/yaml_load_check.py
edx_lint/pylint/events_annotation/__init__.py
edx_lint/pylint/events_annotation/events_annotation_check.py
edx_lint/pylint/filters_docstring/__init__.py
edx_lint/pylint/filters_docstring/filters_docstring_check.py
edx_lint/pylint/unittest_assert/__init__.py
edx_lint/pylint/unittest_assert/unittest_assert_check.py
test/plugins/__init__.py
test/plugins/conftest.py
test/plugins/pylint_test.py
test/plugins/test_annotations_check.py
test/plugins/test_common.py
test/plugins/test_getattr_check.py
test/plugins/test_i18n_check.py
test/plugins/test_ignore_long_lines.py
test/plugins/test_layered_test_check.py
test/plugins/test_range_check.py
test/plugins/test_right_assert_check.py
test/plugins/test_super_check.py
test/plugins/test_unittest_assert_check.py
test/plugins/test_yaml_load_check.py
edx_lint-5.6.0.dist-info/LICENSE.txt
edx_lint-5.6.0.dist-info/METADATA
edx_lint-5.6.0.dist-info/NOTICE.txt
edx_lint-5.6.0.dist-info/WHEEL
edx_lint-5.6.0.dist-info/entry_points.txt
edx_lint-5.6.0.dist-info/top_level.txt
edx_lint-5.6.0.dist-info/RECORD
