Metadata-Version: 2.1
Name: edx-lint
Version: 5.6.0
Summary: edX-authored pylint checkers
Home-page: https://github.com/openedx/edx-lint
Author: edX
Author-email: oscm@edx.org
License: Apache
Classifier: Environment :: Console
Classifier: Intended Audience :: Developers
Classifier: License :: OSI Approved :: Apache Software License
Classifier: Operating System :: OS Independent
Classifier: Programming Language :: Python :: 3.12
Classifier: Topic :: Software Development :: Quality Assurance
License-File: LICENSE.txt
License-File: NOTICE.txt
Requires-Dist: click
Requires-Dist: click-log
Requires-Dist: code-annotations>=1.1.0
Requires-Dist: pylint
Requires-Dist: pylint-celery
Requires-Dist: pylint-django
Requires-Dist: six
